<annotation>
	<folder>Barack_Obama</folder>
	<filename>brak_011.jpg</filename>
	<path>C:\Users\Anaconda\OneDrive\Desktop\FDI\images\Dataset\Dataset\Barack_Obama\brak_011.jpg</path>
	<source>
		<database>Unknown</database>
	</source>
	<size>
		<width>306</width>
		<height>165</height>
		<depth>3</depth>
	</size>
	<segmented>0</segmented>
	<object>
		<name>Barack_Obama</name>
		<pose>Unspecified</pose>
		<truncated>0</truncated>
		<difficult>0</difficult>
		<bndbox>
			<xmin>117</xmin>
			<ymin>2</ymin>
			<xmax>179</xmax>
			<ymax>77</ymax>
		</bndbox>
	</object>
</annotation>
